sigmf_toolkit/__init__.py
sigmf_toolkit/gr_meta_to_sigmf.py
sigmf_toolkit/raw_to_sigmf.py
sigmf_toolkit/sigmf_pcap_annotate.py
sigmf_toolkit/sigmf_time_crop.py
sigmf_toolkit/time.py
sigmf_toolkit-0.2.0.dist-info/METADATA
sigmf_toolkit-0.2.0.dist-info/WHEEL
sigmf_toolkit-0.2.0.dist-info/entry_points.txt
sigmf_toolkit-0.2.0.dist-info/licenses/LICENSE
sigmf_toolkit-0.2.0.dist-info/RECORD
