Metadata-Version: 2.4
Name: sigmf-toolkit
Version: 0.2.0
Summary: Tools to work with SigMF files
Author-email: Daniel Estevez <daniel@destevez.net>
Maintainer-email: Daniel Estevez <daniel@destevez.net>
License-File: LICENSE
Keywords: sigmf
Classifier: Development Status :: 5 - Production/Stable
Classifier: License :: OSI Approved :: MIT License
Classifier: Operating System :: OS Independent
Classifier: Programming Language :: Python :: 3
Classifier: Topic :: Communications :: Ham Radio
Classifier: Topic :: Scientific/Engineering
Requires-Python: >=3.8
Requires-Dist: numpy
Requires-Dist: scapy>=2.6
Requires-Dist: sigmf>=1.2.10
